substrate_telemetry_client/__init__.py
substrate_telemetry_client/async_client.py
substrate_telemetry_client/client.py
substrate_telemetry_client/constants.py
substrate_telemetry_client/core.py
substrate_telemetry_client/exceptions.py
substrate_telemetry_client/types.py
substrate_telemetry_client-0.1.2.dist-info/METADATA
substrate_telemetry_client-0.1.2.dist-info/WHEEL
substrate_telemetry_client-0.1.2.dist-info/licenses/LICENSE
substrate_telemetry_client-0.1.2.dist-info/RECORD
