Metadata-Version: 2.4
Name: substrate-telemetry-client
Version: 0.1.2
Summary: A Python client for Substrate telemetry.
Project-URL: Homepage, https://github.com/w3f/substrate-telemetry-client-py
Author-email: W3F SecOps Team <secops@web3.foundation>
License: MIT License
License-File: LICENSE
Classifier: License :: OSI Approved :: MIT License
Classifier: Operating System :: OS Independent
Classifier: Programming Language :: Python :: 3
Requires-Python: >=3.8
Requires-Dist: websockets>=10.0
